stiqueue/__init__.py
stiqueue/peekqueue.py
stiqueue/sqclient.py
stiqueue/sqserver.py
stiqueue-1.3.0.dist-info/LICENSE
stiqueue-1.3.0.dist-info/METADATA
stiqueue-1.3.0.dist-info/WHEEL
stiqueue-1.3.0.dist-info/top_level.txt
stiqueue-1.3.0.dist-info/RECORD
