Metadata-Version: 2.2
Name: stiqueue
Version: 1.3.0
Summary: StiQueue is a lightweight messaging queue system designed to be simple, flexible, and easy to use.
Home-page: https://github.com/ahmad88me/stiqueue
Author: Ahmad Alobaid
Author-email: Ahmad Alobaid <ahmad88me@gmail.com>
License:                                  Apache License
Project-URL: Homepage, https://github.com/ahmad88me/stiqueue
Project-URL: Issues, https://github.com/ahmad88me/stiqueue/issues
Project-URL: Documentation, https://ahmad88me.github.io/stiqueue/
Classifier: Programming Language :: Python :: 3
Classifier: Operating System :: OS Independent
Classifier: Topic :: Communications
Classifier: License :: OSI Approved :: Apache Software License
Requires-Python: >=3.6
License-File: LICENSE
Dynamic: author
Dynamic: home-page
Dynamic: requires-python
